setup.py
Flask_Imagine.egg-info/PKG-INFO
Flask_Imagine.egg-info/SOURCES.txt
Flask_Imagine.egg-info/dependency_links.txt
Flask_Imagine.egg-info/not-zip-safe
Flask_Imagine.egg-info/requires.txt
Flask_Imagine.egg-info/top_level.txt
flask_imagine/__init__.py
flask_imagine/core.py
flask_imagine/adapters/__init__.py
flask_imagine/adapters/filesystem.py
flask_imagine/adapters/interface.py
flask_imagine/filters/__init__.py
flask_imagine/filters/autorotate.py
flask_imagine/filters/crop.py
flask_imagine/filters/downscale.py
flask_imagine/filters/interface.py
flask_imagine/filters/relative_resize.py
flask_imagine/filters/rotate.py
flask_imagine/filters/thumbnail.py
flask_imagine/filters/upscale.py
flask_imagine/filters/watermark.py
flask_imagine/helpers/__init__.py
flask_imagine/helpers/regex_route.py