Metadata-Version: 1.1
Name: Flask-Imagine
Version: 0.5
Summary: Extension which provides easy image manipulation support in Flask applications.
Home-page: https://github.com/FlaskGuys/Flask-Imagine
Author: Kronas
Author-email: kronas.sw@gmail.com
License: MIT
Platform: UNKNOWN
Classifier: Development Status :: 4 - Beta
Classifier: Intended Audience :: Developers
Classifier: License :: OSI Approved :: MIT License
Classifier: Natural Language :: English
Classifier: Operating System :: OS Independent
Classifier: Programming Language :: Python :: 2
Classifier: Topic :: Software Development :: Libraries :: Python Modules
